{
	"className":	"PtfJob",
	"summary":	"@todo add summary",
	"description":	[{
			"line":	"@todo add description"
		}],
	"cullPrefix":	"JL",
	"attributes":	[{
			"name":	"job_ID",
			"summary":	"@todo add summary",
			"description":	[{
					"line":	"@todo add description"
				}],
			"type":	"lUlongT",
			"flags":	[]
		}, {
			"name":	"OS_job_list",
			"summary":	"@todo add summary",
			"description":	[{
					"line":	"@todo add description"
				}],
			"type":	"lListT",
			"subClassName":	"JO",
			"subCullPrefix":	"JO",
			"flags":	[]
		}, {
			"name":	"state",
			"summary":	"@todo add summary",
			"description":	[{
					"line":	"@todo add description"
				}],
			"type":	"lUlongT",
			"flags":	[]
		}, {
			"name":	"tickets",
			"summary":	"@todo add summary",
			"description":	[{
					"line":	"@todo add description"
				}],
			"type":	"lUlongT",
			"flags":	[]
		}, {
			"name":	"share",
			"summary":	"@todo add summary",
			"description":	[{
					"line":	"@todo add description"
				}],
			"type":	"lDoubleT",
			"flags":	[]
		}, {
			"name":	"ticket_share",
			"summary":	"@todo add summary",
			"description":	[{
					"line":	"@todo add description"
				}],
			"type":	"lDoubleT",
			"flags":	[]
		}, {
			"name":	"timeslice",
			"summary":	"@todo add summary",
			"description":	[{
					"line":	"@todo add description"
				}],
			"type":	"lDoubleT",
			"flags":	[]
		}, {
			"name":	"usage",
			"summary":	"@todo add summary",
			"description":	[{
					"line":	"@todo add description"
				}],
			"type":	"lDoubleT",
			"flags":	[]
		}, {
			"name":	"old_usage_value",
			"summary":	"@todo add summary",
			"description":	[{
					"line":	"@todo add description"
				}],
			"type":	"lDoubleT",
			"flags":	[]
		}, {
			"name":	"adjusted_usage",
			"summary":	"@todo add summary",
			"description":	[{
					"line":	"@todo add description"
				}],
			"type":	"lDoubleT",
			"flags":	[]
		}, {
			"name":	"last_usage",
			"summary":	"@todo add summary",
			"description":	[{
					"line":	"@todo add description"
				}],
			"type":	"lDoubleT",
			"flags":	[]
		}, {
			"name":	"old_usage",
			"summary":	"@todo add summary",
			"description":	[{
					"line":	"@todo add description"
				}],
			"type":	"lDoubleT",
			"flags":	[]
		}, {
			"name":	"proportion",
			"summary":	"@todo add summary",
			"description":	[{
					"line":	"@todo add description"
				}],
			"type":	"lDoubleT",
			"flags":	[]
		}, {
			"name":	"adjusted_proportion",
			"summary":	"@todo add summary",
			"description":	[{
					"line":	"@todo add description"
				}],
			"type":	"lDoubleT",
			"flags":	[]
		}, {
			"name":	"adjusted_current_proportion",
			"summary":	"@todo add summary",
			"description":	[{
					"line":	"@todo add description"
				}],
			"type":	"lDoubleT",
			"flags":	[]
		}, {
			"name":	"actual_proportion",
			"summary":	"@todo add summary",
			"description":	[{
					"line":	"@todo add description"
				}],
			"type":	"lDoubleT",
			"flags":	[]
		}, {
			"name":	"diff_proportion",
			"summary":	"@todo add summary",
			"description":	[{
					"line":	"@todo add description"
				}],
			"type":	"lDoubleT",
			"flags":	[]
		}, {
			"name":	"last_proportion",
			"summary":	"@todo add summary",
			"description":	[{
					"line":	"@todo add description"
				}],
			"type":	"lDoubleT",
			"flags":	[]
		}, {
			"name":	"curr_pri",
			"summary":	"@todo add summary",
			"description":	[{
					"line":	"@todo add description"
				}],
			"type":	"lDoubleT",
			"flags":	[]
		}, {
			"name":	"pri",
			"summary":	"@todo add summary",
			"description":	[{
					"line":	"@todo add description"
				}],
			"type":	"lLongT",
			"flags":	[]
		}, {
			"name":	"procfd",
			"summary":	"@todo add summary",
			"description":	[{
					"line":	"@todo add description"
				}],
			"type":	"lUlongT",
			"flags":	[]
		}, {
			"name":	"interactive",
			"summary":	"@todo add summary",
			"description":	[{
					"line":	"@todo add description"
				}],
			"type":	"lUlongT",
			"flags":	[]
		}]
}
